setup.py
tsviewer/__init__.py
tsviewer/__main__.py
tsviewer/infopane.py
tsviewer/log.py
tsviewer/viewer.py
tsviewer.egg-info/PKG-INFO
tsviewer.egg-info/SOURCES.txt
tsviewer.egg-info/dependency_links.txt
tsviewer.egg-info/entry_points.txt
tsviewer.egg-info/not-zip-safe
tsviewer.egg-info/requires.txt
tsviewer.egg-info/top_level.txt
tsviewer/icon/camera.png
tsviewer/icon/file.png
tsviewer/icon/frame-first.png
tsviewer/icon/frame-last.png
tsviewer/icon/frame-next.png
tsviewer/icon/frame-previous.png
tsviewer/icon/graph.png
tsviewer/icon/hidden.png
tsviewer/icon/legend.png
tsviewer/icon/plot-scale.png
tsviewer/icon/random.png