Metadata-Version: 1.1
Name: tsviewer
Version: 0.1.0
Summary: A GUI for visualizing time series data
Home-page: https://github.com/sswan/tsviewer
Author: Scot Swan, Tim Fuller
Author-email: scot.swan@gmail.com, timothy.fuller@utah.edu
License: MIT
Platform: UNKNOWN
Classifier: Development Status :: 3 - Alpha
Classifier: Environment :: X11 Applications
Classifier: Intended Audience :: Science/Research
Classifier: License :: OSI Approved :: MIT License
Classifier: Natural Language :: English
Classifier: Operating System :: OS Independent
Classifier: Programming Language :: Python :: 2 :: Only
Classifier: Programming Language :: Python :: 2.7
Classifier: Topic :: Scientific/Engineering
Classifier: Topic :: Scientific/Engineering :: Information Analysis
Classifier: Topic :: Scientific/Engineering :: Visualization
Classifier: Topic :: Utilities
